plan_tools/__init__.py
plan_tools/entry_point.py
plan_tools/runtime.py
plan_tools/tests/__init__.py
plan_tools/tests/test_entry_point.py
plan_tools/tests/test_runtime.py
PLAN_Tools-0.7.dist-info/METADATA
PLAN_Tools-0.7.dist-info/WHEEL
PLAN_Tools-0.7.dist-info/entry_points.txt
PLAN_Tools-0.7.dist-info/top_level.txt
PLAN_Tools-0.7.dist-info/RECORD
