Metadata-Version: 2.1
Name: PLAN-Tools
Version: 0.7
Summary: A set of tools to help with Pip Links And Nonsense
Home-page: https://github.com/Myoldmopar/PlanTools
Author: Edwin Lee, for NREL, for United States Department of Energy
License: ModifiedBSD
Keywords: energyplus
Platform: UNKNOWN
Requires-Python: >=3.5
